koning/__main__.py
koning/bus.py
koning/command.py
koning/define.py
koning/error.py
koning/event.py
koning/json.py
koning/locks.py
koning/object.py
koning/parser.py
koning/persist.py
koning/reactor.py
koning/repeater.py
koning/run.py
koning/thread.py
koning/utils.py
koning/modules/__init__.py
koning/modules/cmd.py
koning/modules/dbg.py
koning/modules/err.py
koning/modules/flt.py
koning/modules/irc.py
koning/modules/log.py
koning/modules/mdl.py
koning/modules/mod.py
koning/modules/req.py
koning/modules/rss.py
koning/modules/shp.py
koning/modules/sts.py
koning/modules/tdo.py
koning/modules/thr.py
koning/modules/udp.py
koning/modules/wsd.py
koning-61.data/data/share/doc/koning/20140730_011.jpg
koning-61.data/data/share/doc/koning/20151029_004.jpg
koning-61.data/data/share/doc/koning/ECHAabilify.png
koning-61.data/data/share/doc/koning/ECHAclozapine.png
koning-61.data/data/share/doc/koning/ECHAhaldol.png
koning-61.data/data/share/doc/koning/ECHAhaloperidol.png
koning-61.data/data/share/doc/koning/ECHAzyprexa.png
koning-61.data/data/share/doc/koning/OTP1.png
koning-61.data/data/share/doc/koning/OTP2.png
koning-61.data/data/share/doc/koning/advocatenemails
koning-61.data/data/share/doc/koning/advocatenemails.1
koning-61.data/data/share/doc/koning/advocatenemails.2
koning-61.data/data/share/doc/koning/advocatenemails.3
koning-61.data/data/share/doc/koning/advocatenemails.4
koning-61.data/data/share/doc/koning/aes.ico
koning-61.data/data/share/doc/koning/beuker.rst
koning-61.data/data/share/doc/koning/beuker2.jpg
koning-61.data/data/share/doc/koning/beuker2.rst
koning-61.data/data/share/doc/koning/bevestigd.jpg
koning-61.data/data/share/doc/koning/bevestigd3.jpg
koning-61.data/data/share/doc/koning/bewijsgif.rst
koning-61.data/data/share/doc/koning/bewijsgif3.jpg
koning-61.data/data/share/doc/koning/bewijsgif4.jpg
koning-61.data/data/share/doc/koning/bijwerkingen.rst
koning-61.data/data/share/doc/koning/clozapine.rst
koning-61.data/data/share/doc/koning/conf.py
koning-61.dist-info/METADATA
koning-61.dist-info/WHEEL
koning-61.dist-info/entry_points.txt
koning-61.dist-info/top_level.txt
koning-61.dist-info/zip-safe
koning-61.dist-info/RECORD
