Metadata-Version: 2.1
Name: koning
Version: 61
Summary: ANTIPSYCHOTICA - AKATHISIA - KATATONIE - SEDERING - SHOCKS - LETHALE KATATONIE
Author-email: Bart Thate <bthate@dds.nl>
License: Public Domain
Project-URL: home, https://pypi.org/project/koning
Project-URL: bugs, https://github.com/bthate/koning/issues
Project-URL: source, https://github.com/bthate/koning
Classifier: Development Status :: 3 - Alpha
Classifier: License :: Public Domain
Classifier: Operating System :: Unix
Classifier: Programming Language :: Python
Classifier: Topic :: Utilities
Provides-Extra: dev
